<annotation>
	<folder>roses</folder>
	<filename>12238827553_cf427bfd51_n.jpg</filename>
	<path>I:\FlowerDatset\roses\12238827553_cf427bfd51_n.jpg</path>
	<source>
		<database>Unknown</database>
	</source>
	<size>
		<width>320</width>
		<height>254</height>
		<depth>3</depth>
	</size>
	<segmented>0</segmented>
	<object>
		<name>rose</name>
		<pose>Unspecified</pose>
		<truncated>0</truncated>
		<difficult>0</difficult>
		<bndbox>
			<xmin>69</xmin>
			<ymin>60</ymin>
			<xmax>131</xmax>
			<ymax>108</ymax>
		</bndbox>
	</object>
	<object>
		<name>rose</name>
		<pose>Unspecified</pose>
		<truncated>0</truncated>
		<difficult>0</difficult>
		<bndbox>
			<xmin>166</xmin>
			<ymin>55</ymin>
			<xmax>214</xmax>
			<ymax>95</ymax>
		</bndbox>
	</object>
	<object>
		<name>rose</name>
		<pose>Unspecified</pose>
		<truncated>0</truncated>
		<difficult>0</difficult>
		<bndbox>
			<xmin>211</xmin>
			<ymin>41</ymin>
			<xmax>243</xmax>
			<ymax>103</ymax>
		</bndbox>
	</object>
	<object>
		<name>rose</name>
		<pose>Unspecified</pose>
		<truncated>0</truncated>
		<difficult>0</difficult>
		<bndbox>
			<xmin>126</xmin>
			<ymin>9</ymin>
			<xmax>203</xmax>
			<ymax>60</ymax>
		</bndbox>
	</object>
</annotation>
